{
  "receipt_id": "8a8601d69a8502fb",
  "job_id": "a8bf200c-64fd-47",
  "agent_id": "42ccaac5",
  "status": "success",
  "input_hash": "",
  "output_hash": "94f4843cd0705652bd2af5debfa2f311e94b7069e66976f73dc9b851ccc6cb33",
  "proof": {
    "job_id": "a8bf200c-64fd-47",
    "gpu": "Unknown GPU",
    "runtime_seconds": 0.4849257469177246,
    "input_hash": "",
    "output_hash": "94f4843cd0705652bd2af5debfa2f311e94b7069e66976f73dc9b851ccc6cb33",
    "timestamp": "2026-06-27T17:39:17.331699",
    "metrics": {
      "job_id": "a8bf200c-64fd-47",
      "gpu_name": "Unknown GPU",
      "gpu_memory_total": 0,
      "gpu_memory_used": 0,
      "cpu_percent": 14.3,
      "memory_percent": 89.0,
      "runtime_seconds": 8.04270052909851,
      "timestamp": "2026-06-27T17:39:17.314933+00:00"
    },
    "signature": "2d089b30c30dfc795eb6bef87373720462adf2ca8d433bef6669ca0a21b8bc12",
    "verified": true
  },
  "issued_at": "2026-06-27T17:39:17.335643"
}